<?xml version='1.0'?>

<annotated version="1.0">
  <meta>
    <transcriber>ug</transcriber>
    <date>2009-11-18</date>
    <place>Ile-Ife</place>
    <author><gender>m</gender><age>?</age><ethnic-group>Yoruba</ethnic-group></author>
  </meta>
  <text>
    <heading>XXX UNIVERSITY</heading>
    <heading>XXX, NIGERIA</heading>
    <p>Department of Linguistics and African Languages</p>
    <p><object/></p>
    <p>Phone: <x-anonym-x/></p>
    <p>E-mail: <x-anonym-x type="e-mail"/></p>
    <p>Date: November 18, 2009</p>
    <heading>CURRENT PERSPECTIVES IN PHONO-SYNTAX AND 
    DIALECTOLOGY</heading>
    <p>Dear Contributors,</p>
    <p><italics>Re: Submission of manuscript for publication in Current 
    Perspectives in Phono-Syntax and Dialectology edited by 
    <x-anonym-x type="family-name"/> and 
    <x-anonym-x type="family-name"/></italics></p>
    <p>We acknowledge the receipt of your manuscript sent for 
    publication in <italics>Current Perspectives in Phono-Syntax and 
    Dialectology</italics>. We also acknowledge the receipt of your 
    reworked manuscript after our assessors&apos; comments. We are 
    happy to inform you that your contribution has been accepted as a 
    Chapter in the book entitled Current Perspectives in Phono-Syntax 
    and Dialectology. The book is due for publication before the end of 
    2009 by <x-anonym-x type="organisation"/> University Press, 
    <x-anonym-x type="location"/>. The publishers will however require 
    camera ready copy of the manuscript for further processing, putting 
    the cost of copy editing on the shoulders of individual 
    contributors.</p>
    <p>We shall be glad if you pay into the account below* the sum of $ 
    <x-anonym-x/> to defray the cost of assessment fees, copy editing 
    and postage on or before 10<superscript>th</superscript> December, 
    2009. Efforts are underway (and it is 100% certain) to make the 
    book available to you and the public on or before 
    21<superscript>st</superscript> December 2009. Thank you for your 
    understanding. Please after effecting the payment, do send us 
    definite postage address for authors complimentary copies (use the 
    email addresses above). Thank you.</p>
    <p>*Name of Bank: Bank PLC</p>
    <p>Branch: <x-anonym-x /> Branch</p>
    <p>Account Name/Holder Dr<punctuation>.</punctuation> <x-anonym-x type="first-name"/> 
    <x-anonym-x type="first-name"/> <x-anonym-x type="family-name"/></p>
    <p>Account Number: <x-anonym-x /></p>
    <p>Please note that the account is USD denominated only.</p>
    <p>Sincerely yours,</p>
    <p />
    <p><boldface>Dr.</boldface><punctuation>.</punctuation> <x-anonym-x type="first-name"/> 
    <x-anonym-x type="first-name"/> <x-anonym-x type="family-name"/></p>
    <p>Co-Editor</p>
    <p><italics>Current Perspectives in Phono-Syntax and 
    Dialectology</italics></p>
  </text>
</annotated>
